klyqa/__init__.py
klyqa/cloud.py
klyqa/device.py
klyqa/exceptions.py
klyqa/models.py
klyqa-1.0.10.dist-info/LICENSE
klyqa-1.0.10.dist-info/METADATA
klyqa-1.0.10.dist-info/WHEEL
klyqa-1.0.10.dist-info/top_level.txt
klyqa-1.0.10.dist-info/RECORD
