Metadata-Version: 2.1
Name: klyqa
Version: 1.0.10
Summary: Connection Library for Klyqa REST enabled devices
Home-page: https://gitlab.com/ninharp/python-klyqa
Author: ninharp
Author-email: zukunpht@gmail.com
Project-URL: Bug Tracker, https://gitlab.com/ninharp/python-klyqa/issues
Project-URL: repository, https://gitlab.com/ninharp/python-klyqa
Classifier: Programming Language :: Python :: 3
Classifier: License :: OSI Approved :: MIT License
Classifier: Operating System :: OS Independent
Requires-Python: >=3.12
License-File: LICENSE
Requires-Dist: zeroconf
Requires-Dist: aiohttp
Requires-Dist: orjson
Requires-Dist: mashumaro
